recipe_tagger/__init__.py
recipe_tagger/foodcategory.py
recipe_tagger/recipe_tagger.py
recipe_tagger/data/ingredient_embedding.npy
recipe_tagger-0.1.0.dist-info/METADATA
recipe_tagger-0.1.0.dist-info/WHEEL
recipe_tagger-0.1.0.dist-info/top_level.txt
recipe_tagger-0.1.0.dist-info/RECORD
